mfp/__init__.py
mfp/main.py
mfp/utils.py
mfp/mfp_sub/__init__.py
mfp/mfp_sub/times.py
mfp/mfp_sub/times_config.py
mfp-0.2.7.dist-info/METADATA
mfp-0.2.7.dist-info/WHEEL
mfp-0.2.7.dist-info/top_level.txt
mfp-0.2.7.dist-info/RECORD
