Metadata-Version: 2.2
Name: mfp
Version: 0.2.7
Summary: My first package
Author: Ben van Vliet
License: MIT License
Keywords: mfp
Classifier: Development Status :: 2 - Pre-Alpha
Classifier: Intended Audience :: Developers
Classifier: License :: OSI Approved :: MIT License
Classifier: Natural Language :: English
Classifier: Programming Language :: Python :: 3
Classifier: Programming Language :: Python :: 3.12
Requires-Python: >=3.12
Requires-Dist: loguru>=0.7.3
Requires-Dist: pandas>=2.2.3
Requires-Dist: polars>=1.22.0
Requires-Dist: psycopg2>=2.9.10
Requires-Dist: python-dotenv>=1.0.1
Requires-Dist: requests>=2.32.3
Requires-Dist: ruff>=0.9.7
Requires-Dist: scikit-learn>=1.6.1
Requires-Dist: sqlalchemy>=2.0.38
Requires-Dist: tabulate>=0.9.0
